{
  "Repas1": {
    "Titre": "Curry de lentilles corail",
    "Ingrédients": [
      "lentilles",
      "lait_coco",
      "epinards",
      "patate_douce",
      "gingembre"
    ],
    "État": "proposé"
  },
  "Repas2": {
    "Titre": "Salade de pois chiches croustillants",
    "Ingrédients": [
      "pois_chiches",
      "tomates",
      "concombre",
      "persil",
      "citron"
    ],
    "État": "proposé"
  },
  "Repas3": {
    "Titre": "Saumon au four et quinoa",
    "Ingrédients": [
      "saumon",
      "quinoa",
      "courgettes",
      "citron",
      "aneth"
    ],
    "État": "proposé"
  },
  "Repas4": {
    "Titre": "Tofu fumé et brocoli sauté",
    "Ingrédients": [
      "tofu",
      "brocoli",
      "champignons",
      "ail",
      "tamari"
    ],
    "État": "proposé"
  },
  "Repas5": {
    "Titre": "Soupe minestrone aux haricots blancs",
    "Ingrédients": [
      "haricots_blancs",
      "carottes",
      "blettes",
      "tomates",
      "origan"
    ],
    "État": "proposé"
  },
  "Repas6": {
    "Titre": "Cabillaud vapeur et légumes racines",
    "Ingrédients": [
      "cabillaud",
      "panais",
      "carottes",
      "poireau",
      "huile_olive"
    ],
    "État": "proposé"
  },
  "Repas7": {
    "Titre": "Risotto de sarrasin aux champignons",
    "Ingrédients": [
      "sarrasin",
      "champignons",
      "bouillon_legumes",
      "petits_pois",
      "ciboulette"
    ],
    "État": "proposé"
  }
}
